subpackage1/__init__.py
subpackage1/module1.py
subpackage2/__init__.py
subpackage2/module2.py
test88641-0.1.2.dist-info/METADATA
test88641-0.1.2.dist-info/WHEEL
test88641-0.1.2.dist-info/top_level.txt
test88641-0.1.2.dist-info/RECORD
