Metadata-Version: 2.1
Name: test88641
Version: 0.1.2
Summary: A test upload
Home-page: https://github.com/ftnworld/test88641
Author: user8864
License: UNKNOWN
Platform: UNKNOWN
Classifier: Programming Language :: Python :: 3
Classifier: License :: OSI Approved :: MIT License
Classifier: Operating System :: OS Independent
Requires-Python: >=3.6
Requires-Dist: matplotlib
Requires-Dist: numpy
Requires-Dist: pandas
